<?xml version="1.0" encoding="UTF-8" standalone="yes"?>
<reference:reference xmlns:seller="http://services.mobile.de/schema/seller" xmlns:ad="http://services.mobile.de/schema/ad" xmlns:financing="http://services.mobile.de/schema/common/financing-1.0" xmlns:reference="http://services.mobile.de/schema/reference" xmlns:resource="http://services.mobile.de/schema/resource"><reference:item key="LEATHER" url="https://services.mobile.de/refdata/interiorTypes/LEATHER"><resource:local-description xml-lang="en">Full leather</resource:local-description></reference:item><reference:item key="PARTIAL_LEATHER" url="https://services.mobile.de/refdata/interiorTypes/PARTIAL_LEATHER"><resource:local-description xml-lang="en">Part leather</resource:local-description></reference:item><reference:item key="FABRIC" url="https://services.mobile.de/refdata/interiorTypes/FABRIC"><resource:local-description xml-lang="en">Cloth</resource:local-description></reference:item><reference:item key="VELOUR" url="https://services.mobile.de/refdata/interiorTypes/VELOUR"><resource:local-description xml-lang="en">Velour</resource:local-description></reference:item><reference:item key="ALCANTARA" url="https://services.mobile.de/refdata/interiorTypes/ALCANTARA"><resource:local-description xml-lang="en">Alcantara</resource:local-description></reference:item><reference:item key="OTHER_INTERIOR_TYPE" url="https://services.mobile.de/refdata/interiorTypes/OTHER_INTERIOR_TYPE"><resource:local-description xml-lang="en">Other</resource:local-description></reference:item></reference:reference>